noaa_object_data_delivery_pipeline/generated/__init__.py
noaa_object_data_delivery_pipeline/generated/__init__.py.tmp
noaa_object_data_delivery_pipeline/generated/environment_base.py
noaa_object_data_delivery_pipeline/generated/environment_base.py.tmp
noaa_object_data_delivery_pipeline/generated/pipeline/pipeline_base.py
noaa_object_data_delivery_pipeline/generated/pipeline/pipeline_base.py.tmp
noaa_object_data_delivery_pipeline/generated/step/__init__.py
noaa_object_data_delivery_pipeline/generated/step/__init__.py.tmp
noaa_object_data_delivery_pipeline/generated/step/abstract_data_action.py
noaa_object_data_delivery_pipeline/generated/step/abstract_data_action.py.tmp
noaa_object_data_delivery_pipeline/generated/step/abstract_pipeline_step.py
noaa_object_data_delivery_pipeline/generated/step/abstract_pipeline_step.py.tmp
noaa_object_data_delivery_pipeline/generated/step/ingest_data_base.py
noaa_object_data_delivery_pipeline/generated/step/ingest_data_base.py.tmp
noaa_object_data_delivery_pipeline/noaa_object_data_delivery_pipeline_driver.py
noaa_object_data_delivery_pipeline/resources/apps/aws-config.yaml
noaa_object_data_delivery_pipeline/resources/apps/noaa-object-data-delivery-pipeline-base-values.yaml
noaa_object_data_delivery_pipeline/resources/apps/noaa-object-data-delivery-pipeline-ci-values.yaml
noaa_object_data_delivery_pipeline/resources/apps/noaa-object-data-delivery-pipeline-dev-values.yaml
noaa_object_data_delivery_pipeline/step/__init__.py
noaa_object_data_delivery_pipeline/step/abstract_data_action_impl.py
noaa_object_data_delivery_pipeline/step/ingest_data.py
noaa_object_data_delivery_pipeline-1.0.0.dev1717086190.dist-info/LICENSE.txt
noaa_object_data_delivery_pipeline-1.0.0.dev1717086190.dist-info/METADATA
noaa_object_data_delivery_pipeline-1.0.0.dev1717086190.dist-info/WHEEL
noaa_object_data_delivery_pipeline-1.0.0.dev1717086190.dist-info/RECORD
