Metadata-Version: 2.1
Name: noaa-object-data-delivery-pipeline
Version: 1.0.0.dev1717086190
Summary: Pipeline for ingesting a sample dataset
Author: Your Name
Author-email: you@example.com
Requires-Python: >=3.11.4,<4.0.0
Classifier: Programming Language :: Python :: 3
Classifier: Programming Language :: Python :: 3.12
Requires-Dist: confluent-kafka (==2.1.1)
Requires-Dist: extensions-data-delivery-spark-py (==1.6.1)
Requires-Dist: extensions-encryption-vault-python (==1.6.1)
Requires-Dist: foundation-core-python (==1.6.1)
Requires-Dist: foundation-encryption-policy-python (==1.6.1)
Requires-Dist: foundation-pdp-client-python (==1.6.1)
Requires-Dist: jsonpickle (>=2.1.0,<3.0.0)
Requires-Dist: kafka-python (>=2.0.2,<3.0.0)
Requires-Dist: krausening (>=19)
Requires-Dist: pyspark (==3.4.0)
Requires-Dist: pyyaml (>=6.0,<7.0)
